ProsperDatareader-2.1.0.dist-info/DESCRIPTION.rst
ProsperDatareader-2.1.0.dist-info/METADATA
ProsperDatareader-2.1.0.dist-info/RECORD
ProsperDatareader-2.1.0.dist-info/WHEEL
ProsperDatareader-2.1.0.dist-info/metadata.json
ProsperDatareader-2.1.0.dist-info/top_level.txt
prosper/datareader/__init__.py
prosper/datareader/_version.py
prosper/datareader/coins.py
prosper/datareader/config.py
prosper/datareader/exceptions.py
prosper/datareader/news.py
prosper/datareader/stocks.py
prosper/datareader/utils.py
prosper/datareader/version.txt
prosper/datareader/cryptocompare/__init__.py
prosper/datareader/cryptocompare/quotes.py
prosper/datareader/hitbtc/__init__.py
prosper/datareader/hitbtc/quotes.py
prosper/datareader/iex/__init__.py
prosper/datareader/intrinio/__init__.py
prosper/datareader/intrinio/auth.py
prosper/datareader/robinhood/__init__.py
prosper/datareader/robinhood/news.py
prosper/datareader/robinhood/quotes.py
prosper/datareader/yahoo/__init__.py
prosper/datareader/yahoo/news.py
