Metadata-Version: 2.0
Name: ProsperDatareader
Version: 2.1.0
Summary: Data parser utilities for Prosper projects
Home-page: https://github.com/EVEprosper/ProsperDatareader
Author: John Purcell
Author-email: prospermarketshow@gmail.com
License: MIT
Download-URL: https://pypi.python.org/pypi/ProsperDatareader
Keywords: prosper eve-online data REST
Platform: UNKNOWN
Classifier: Programming Language :: Python :: 3.5
Classifier: Programming Language :: Python :: 3.6
Requires-Dist: prospercommon
Requires-Dist: pandas
Requires-Dist: requests
Requires-Dist: six
Requires-Dist: semantic-version
Requires-Dist: demjson (~=2.2.4)
Requires-Dist: feedparser
Provides-Extra: dev
Requires-Dist: pandas-datareader; extra == 'dev'
Requires-Dist: sphinx; extra == 'dev'
Requires-Dist: sphinxcontrib-napoleon; extra == 'dev'
Requires-Dist: semantic-version; extra == 'dev'
Provides-Extra: nltk
Requires-Dist: nltk; extra == 'nltk'
